[
  {
    "name": "theme_info",
    "theme_name": "Misu",
    "theme_version": "1.0.0",
    "theme_author": "Misu",
    "theme_documentation_url": "https://help.shopify.com/manual/online-store/themes",
    "theme_support_url": "https://support.shopify.com/"
  },
  {
    "name": "t:settings.logo.name",
    "settings": [
      {
        "type": "image_picker",
        "id": "logo",
        "label": "t:settings.logo.logo"
      },
      {
        "type": "header",
        "content": "t:settings.logo.desktop"
      },
      {
        "type": "range",
        "id": "logo_width",
        "min": 50,
        "max": 300,
        "step": 10,
        "default": 120,
        "unit": "px",
        "label": "t:settings.logo.logo_width"
      },
      {
        "type": "header",
        "content": "t:settings.logo.mobile"
      },
      {
        "type": "range",
        "id": "logo_width_mobile",
        "min": 40,
        "max": 200,
        "step": 10,
        "default": 100,
        "unit": "px",
        "label": "t:settings.logo.logo_width"
      },
      {
        "type": "image_picker",
        "id": "favicon",
        "label": "t:settings.logo.favicon",
        "info": "t:settings.logo.favicon_info"
      }
    ]
  },
  {
    "name": "t:settings.colors.name",
    "settings": [
      {
        "type": "header",
        "content": "t:settings.colors.primary_colors"
      },
      {
        "type": "color",
        "id": "color_background",
        "default": "#FAFAF8",
        "label": "t:settings.colors.background"
      },
      {
        "type": "color",
        "id": "color_text",
        "default": "#1A1A1A",
        "label": "t:settings.colors.text"
      },
      {
        "type": "color",
        "id": "color_text_muted",
        "default": "#6B6B6B",
        "label": "t:settings.colors.text_muted"
      },
      {
        "type": "header",
        "content": "t:settings.colors.accent_colors"
      },
      {
        "type": "color",
        "id": "color_primary",
        "default": "#2D5A47",
        "label": "t:settings.colors.primary"
      },
      {
        "type": "color",
        "id": "color_primary_text",
        "default": "#FFFFFF",
        "label": "t:settings.colors.primary_text"
      },
      {
        "type": "color",
        "id": "color_secondary",
        "default": "#E8E4DF",
        "label": "t:settings.colors.secondary"
      },
      {
        "type": "color",
        "id": "color_secondary_text",
        "default": "#1A1A1A",
        "label": "t:settings.colors.secondary_text"
      },
      {
        "type": "header",
        "content": "t:settings.colors.utility_colors"
      },
      {
        "type": "color",
        "id": "color_border",
        "default": "#E5E5E5",
        "label": "t:settings.colors.border"
      },
      {
        "type": "color",
        "id": "color_error",
        "default": "#D64545",
        "label": "t:settings.colors.error"
      },
      {
        "type": "color",
        "id": "color_success",
        "default": "#2D5A47",
        "label": "t:settings.colors.success"
      }
    ]
  },
  {
    "name": "t:settings.typography.name",
    "settings": [
      {
        "type": "header",
        "content": "t:settings.typography.headings"
      },
      {
        "type": "select",
        "id": "font_heading_type",
        "label": "t:settings.typography.font_type",
        "options": [
          { "value": "custom", "label": "STIX Two Text" },
          { "value": "shopify", "label": "t:settings.typography.shopify_fonts" }
        ],
        "default": "custom"
      },
      {
        "type": "font_picker",
        "id": "font_heading",
        "default": "inter_n6",
        "label": "t:settings.typography.heading_font"
      },
      {
        "type": "select",
        "id": "font_heading_weight",
        "label": "t:settings.typography.heading_weight",
        "options": [
          { "value": "300", "label": "t:settings.typography.weight_light" },
          { "value": "400", "label": "t:settings.typography.weight_regular" },
          { "value": "500", "label": "t:settings.typography.weight_medium" },
          { "value": "600", "label": "t:settings.typography.weight_semibold" },
          { "value": "700", "label": "t:settings.typography.weight_bold" }
        ],
        "default": "600"
      },
      {
        "type": "header",
        "content": "t:settings.typography.desktop"
      },
      {
        "type": "select",
        "id": "heading_size_scale",
        "label": "t:settings.typography.heading_size",
        "options": [
          { "value": "90", "label": "t:settings.typography.size_small" },
          { "value": "100", "label": "t:settings.typography.size_medium" },
          { "value": "110", "label": "t:settings.typography.size_large" }
        ],
        "default": "100"
      },
      {
        "type": "header",
        "content": "t:settings.typography.mobile"
      },
      {
        "type": "select",
        "id": "heading_size_scale_mobile",
        "label": "t:settings.typography.heading_size",
        "options": [
          { "value": "80", "label": "t:settings.typography.size_small" },
          { "value": "90", "label": "t:settings.typography.size_medium" },
          { "value": "100", "label": "t:settings.typography.size_large" }
        ],
        "default": "90"
      },
      {
        "type": "header",
        "content": "t:settings.typography.body"
      },
      {
        "type": "select",
        "id": "font_body_type",
        "label": "t:settings.typography.font_type",
        "options": [
          { "value": "custom", "label": "STIX Two Text" },
          { "value": "shopify", "label": "t:settings.typography.shopify_fonts" }
        ],
        "default": "custom"
      },
      {
        "type": "font_picker",
        "id": "font_body",
        "default": "inter_n4",
        "label": "t:settings.typography.body_font"
      },
      {
        "type": "select",
        "id": "font_body_weight",
        "label": "t:settings.typography.body_weight",
        "options": [
          { "value": "300", "label": "t:settings.typography.weight_light" },
          { "value": "400", "label": "t:settings.typography.weight_regular" },
          { "value": "500", "label": "t:settings.typography.weight_medium" },
          { "value": "600", "label": "t:settings.typography.weight_semibold" }
        ],
        "default": "400"
      },
      {
        "type": "select",
        "id": "body_size_scale",
        "label": "t:settings.typography.body_size",
        "options": [
          { "value": "90", "label": "t:settings.typography.size_small" },
          { "value": "100", "label": "t:settings.typography.size_medium" },
          { "value": "110", "label": "t:settings.typography.size_large" }
        ],
        "default": "100"
      }
    ]
  },
  {
    "name": "t:settings.layout.name",
    "settings": [
      {
        "type": "select",
        "id": "page_width",
        "label": "t:settings.layout.page_width",
        "options": [
          { "value": "1200", "label": "t:settings.layout.width_narrow" },
          { "value": "1400", "label": "t:settings.layout.width_medium" },
          { "value": "1600", "label": "t:settings.layout.width_wide" }
        ],
        "default": "1400"
      },
      {
        "type": "header",
        "content": "t:settings.layout.desktop"
      },
      {
        "type": "range",
        "id": "page_margin",
        "min": 16,
        "max": 64,
        "step": 4,
        "default": 24,
        "unit": "px",
        "label": "t:settings.layout.page_margin"
      },
      {
        "type": "range",
        "id": "section_spacing",
        "min": 0,
        "max": 120,
        "step": 8,
        "default": 0,
        "unit": "px",
        "label": "t:settings.layout.section_spacing"
      },
      {
        "type": "header",
        "content": "t:settings.layout.mobile"
      },
      {
        "type": "range",
        "id": "page_margin_mobile",
        "min": 12,
        "max": 32,
        "step": 4,
        "default": 16,
        "unit": "px",
        "label": "t:settings.layout.page_margin"
      },
      {
        "type": "range",
        "id": "section_spacing_mobile",
        "min": 0,
        "max": 80,
        "step": 8,
        "default": 0,
        "unit": "px",
        "label": "t:settings.layout.section_spacing"
      }
    ]
  },
  {
    "name": "t:settings.buttons.name",
    "settings": [
      {
        "type": "range",
        "id": "button_border_radius",
        "min": 0,
        "max": 50,
        "step": 1,
        "default": 50,
        "unit": "px",
        "label": "t:settings.buttons.border_radius"
      },
      {
        "type": "select",
        "id": "button_style",
        "label": "t:settings.buttons.style",
        "options": [
          { "value": "solid", "label": "t:settings.buttons.style_solid" },
          { "value": "outline", "label": "t:settings.buttons.style_outline" }
        ],
        "default": "solid"
      }
    ]
  },
  {
    "name": "t:settings.inputs.name",
    "settings": [
      {
        "type": "range",
        "id": "input_border_radius",
        "min": 0,
        "max": 24,
        "step": 1,
        "default": 8,
        "unit": "px",
        "label": "t:settings.inputs.border_radius"
      },
      {
        "type": "select",
        "id": "input_style",
        "label": "t:settings.inputs.style",
        "options": [
          { "value": "box", "label": "t:settings.inputs.style_box" },
          { "value": "underline", "label": "t:settings.inputs.style_underline" }
        ],
        "default": "box"
      }
    ]
  },
  {
    "name": "t:settings.products.name",
    "settings": [
      {
        "type": "header",
        "content": "t:settings.products.card_settings"
      },
      {
        "type": "select",
        "id": "product_card_style",
        "label": "t:settings.products.card_style",
        "options": [
          { "value": "standard", "label": "t:settings.products.card_standard" },
          { "value": "minimal", "label": "t:settings.products.card_minimal" }
        ],
        "default": "standard"
      },
      {
        "type": "checkbox",
        "id": "product_show_vendor",
        "label": "t:settings.products.show_vendor",
        "default": false
      },
      {
        "type": "checkbox",
        "id": "product_show_secondary_image",
        "label": "t:settings.products.show_secondary_image",
        "default": true
      },
      {
        "type": "header",
        "content": "t:settings.products.badges"
      },
      {
        "type": "checkbox",
        "id": "product_show_sale_badge",
        "label": "t:settings.products.show_sale_badge",
        "default": true
      },
      {
        "type": "checkbox",
        "id": "product_show_soldout_badge",
        "label": "t:settings.products.show_soldout_badge",
        "default": true
      }
    ]
  },
  {
    "name": "t:settings.cart.name",
    "settings": [
      {
        "type": "select",
        "id": "cart_type",
        "label": "t:settings.cart.cart_type",
        "options": [
          { "value": "page", "label": "t:settings.cart.type_page" },
          { "value": "drawer", "label": "t:settings.cart.type_drawer" }
        ],
        "default": "drawer"
      },
      {
        "type": "checkbox",
        "id": "cart_show_free_shipping_bar",
        "label": "t:settings.cart.show_free_shipping_bar",
        "default": true
      },
      {
        "type": "text",
        "id": "cart_free_shipping_threshold",
        "label": "t:settings.cart.free_shipping_threshold",
        "default": "50",
        "info": "t:settings.cart.free_shipping_info"
      }
    ]
  },
  {
    "name": "t:settings.footer.name",
    "settings": [
      {
        "type": "header",
        "content": "t:settings.footer.colors_header"
      },
      {
        "type": "color",
        "id": "footer_background",
        "default": "#1A1A1A",
        "label": "t:settings.footer.background"
      },
      {
        "type": "color",
        "id": "footer_text",
        "default": "#FFFFFF",
        "label": "t:settings.footer.text"
      },
      {
        "type": "color",
        "id": "footer_text_muted",
        "default": "#8A8A8A",
        "label": "t:settings.footer.text_muted"
      },
      {
        "type": "color",
        "id": "footer_accent",
        "default": "#FFFFFF",
        "label": "t:settings.footer.accent"
      },
      {
        "type": "color",
        "id": "footer_border",
        "default": "#333333",
        "label": "t:settings.footer.border"
      },
      {
        "type": "color",
        "id": "footer_button",
        "default": "#FFFFFF",
        "label": "t:settings.footer.button"
      },
      {
        "type": "header",
        "content": "t:settings.footer.background_text_header"
      },
      {
        "type": "color",
        "id": "footer_watermark_color",
        "default": "#2A2A2A",
        "label": "t:settings.footer.watermark_color"
      }
    ]
  },
  {
    "name": "t:settings.social.name",
    "settings": [
      {
        "type": "header",
        "content": "t:settings.social.accounts"
      },
      {
        "type": "text",
        "id": "social_instagram",
        "label": "t:settings.social.instagram",
        "info": "https://instagram.com/shopify"
      },
      {
        "type": "text",
        "id": "social_facebook",
        "label": "t:settings.social.facebook",
        "info": "https://facebook.com/shopify"
      },
      {
        "type": "text",
        "id": "social_twitter",
        "label": "t:settings.social.twitter",
        "info": "https://twitter.com/shopify"
      },
      {
        "type": "text",
        "id": "social_tiktok",
        "label": "t:settings.social.tiktok",
        "info": "https://tiktok.com/@shopify"
      },
      {
        "type": "text",
        "id": "social_youtube",
        "label": "t:settings.social.youtube",
        "info": "https://youtube.com/shopify"
      },
      {
        "type": "text",
        "id": "social_pinterest",
        "label": "t:settings.social.pinterest",
        "info": "https://pinterest.com/shopify"
      }
    ]
  }
]
